autoaicluster/__init__.py
enterprise_cluster_solution/__init__.py
enterprise_cluster_solution/pipeline.py
enterprise_cluster_solution/python_api.py
enterprise_cluster_solution/server.py
enterprise_cluster_solution/modules/__init__.py
enterprise_cluster_solution/ui/index.html
enterprise_cluster_solution/ui/assets/.gitkeep
autoaicluster-0.2.0.dist-info/METADATA
autoaicluster-0.2.0.dist-info/WHEEL
autoaicluster-0.2.0.dist-info/top_level.txt
autoaicluster-0.2.0.dist-info/RECORD
