Metadata-Version: 2.4
Name: autoaicluster
Version: 0.2.0
Summary: Auto AI Clustering: end-to-end segmentation via Python API or local web UI.
Author: Enterprise Cluster Team
License: MIT
Project-URL: Homepage, https://example.com/autoaicluster
Keywords: clustering,automl,segmentation,fastapi,pipeline,visualization
Classifier: Programming Language :: Python :: 3
Classifier: License :: OSI Approved :: MIT License
Classifier: Operating System :: OS Independent
Classifier: Framework :: FastAPI
Classifier: Topic :: Scientific/Engineering :: Artificial Intelligence
Requires-Python: >=3.9
Requires-Dist: fastapi>=0.110
Requires-Dist: uvicorn[standard]>=0.22
Requires-Dist: pandas>=2.0
Requires-Dist: numpy>=1.24
Requires-Dist: scikit-learn>=1.3
Requires-Dist: scikit-learn-extra>=0.3.0
Requires-Dist: plotly>=5.20
Requires-Dist: pydantic>=2.5
Requires-Dist: python-multipart>=0.0.9
Requires-Dist: umap-learn>=0.5.6
